{
  "task": "xml_file_upload", 
  "depends_on": [
    "completed@prepare_metadata_xml"
  ], 
  "tool": "upload", 
  "command": "upload.py", 
  "output": [
    {
      "runtime": {
        "task_start": 1497277775, 
        "task_stop": 1497277790
      }, 
      "worker_id": "worker.1497276150.edd6d833.host.231181a3.10.10.1.7", 
      "task_state": "completed"
    }
  ], 
  "input": {
    "file_name": "bundle.EGAR00001106936.xml", 
    "object_id": "bea6be02-4cc8-5da5-8c22-d9858143c30b", 
    "file_md5sum": "a3035fe96c15282d712b3b65bedb4be0", 
    "file": "/home/ubuntu/jtracker/worker.1497276150.edd6d833.host.231181a3.10.10.1.7/job.EGAR00001106936.LINC-JP.BN04T.EGAN00001085932/task.prepare_metadata_xml/bundle.EGAR00001106936.xml", 
    "file_size": 3655, 
    "bundle_id": "EGAR00001106936"
  }, 
  "runtime": {
    "docker": null
  }
}