{
  "task": "xml_file_upload", 
  "depends_on": [
    "completed@prepare_metadata_xml"
  ], 
  "tool": "upload", 
  "command": "upload.py", 
  "output": [
    {
      "runtime": {
        "task_start": 1496081117, 
        "task_stop": 1496081131
      }, 
      "worker_id": "worker.1495815557.f455bc66.host.bff27a91.10.10.0.223", 
      "task_state": "completed"
    }
  ], 
  "input": {
    "file_name": "bundle.EGAR00001250823.xml", 
    "object_id": "8817d531-ad82-5223-9be2-3c3f1f6ec28d", 
    "file_md5sum": "93263618eae8f20cc676f7969c740dc5", 
    "file": "/home/ubuntu/jtracker/worker.1495815557.f455bc66.host.bff27a91.10.10.0.223/job.EGAR00001250823.PRAD-CA.CPCG0234-F1.EGAN00001239468/task.prepare_metadata_xml/bundle.EGAR00001250823.xml", 
    "file_size": 7391, 
    "bundle_id": "EGAR00001250823"
  }, 
  "runtime": {
    "docker": null
  }
}