{
  "task": "xml_file_upload", 
  "depends_on": [
    "completed@prepare_metadata_xml"
  ], 
  "tool": "upload", 
  "command": "upload.py", 
  "input": {
    "file_name": "bundle.EGAR00001250703.xml", 
    "object_id": "84f93834-9ef0-5039-9e08-2e5da4bb8cbb", 
    "file_md5sum": "{{xml_file_md5sum@prepare_metadata_xml}}", 
    "file": "{{xml_file@prepare_metadata_xml}}", 
    "file_size": "{{xml_file_size@prepare_metadata_xml}}", 
    "bundle_id": "EGAR00001250703"
  }, 
  "runtime": {
    "docker": null
  }
}