{
  "task": "xml_file_upload", 
  "depends_on": [
    "completed@prepare_metadata_xml"
  ], 
  "tool": "upload", 
  "command": "upload.py", 
  "output": [
    {
      "runtime": {
        "task_start": 1497252568, 
        "task_stop": 1497252583
      }, 
      "worker_id": "worker.1497031607.01035bc9.host.231181a3.10.10.1.7", 
      "task_state": "completed"
    }
  ], 
  "input": {
    "file_name": "bundle.EGAR00001195751.xml", 
    "object_id": "c1771e8d-ff2f-568c-9641-7f61b2effafe", 
    "file_md5sum": "37f7455272a52c460cfb7aa6ae279815", 
    "file": "/home/ubuntu/jtracker/worker.1497031607.01035bc9.host.231181a3.10.10.1.7/job.EGAR00001195751.LINC-JP.HCC117T.EGAN00001196886/task.prepare_metadata_xml/bundle.EGAR00001195751.xml", 
    "file_size": 3511, 
    "bundle_id": "EGAR00001195751"
  }, 
  "runtime": {
    "docker": null
  }
}