{
  "task": "xml_file_upload", 
  "depends_on": [
    "completed@prepare_metadata_xml"
  ], 
  "tool": "upload", 
  "command": "upload.py", 
  "output": [
    {
      "runtime": {
        "task_start": 1497047516, 
        "task_stop": 1497047530
      }, 
      "worker_id": "worker.1497031607.01035bc9.host.231181a3.10.10.1.7", 
      "task_state": "completed"
    }
  ], 
  "input": {
    "file_name": "bundle.EGAR00001110096.xml", 
    "object_id": "f80d108f-66f7-521f-b2a7-6dc3cf99d4fd", 
    "file_md5sum": "75d5e7baf5b5c8139395b15bf2b1d5f2", 
    "file": "/home/ubuntu/jtracker/worker.1497031607.01035bc9.host.231181a3.10.10.1.7/job.EGAR00001110096.LINC-JP.HCC8T.EGAN00001085967/task.prepare_metadata_xml/bundle.EGAR00001110096.xml", 
    "file_size": 3659, 
    "bundle_id": "EGAR00001110096"
  }, 
  "runtime": {
    "docker": null
  }
}