{
  "task": "xml_file_upload", 
  "depends_on": [
    "completed@prepare_metadata_xml"
  ], 
  "tool": "upload", 
  "command": "upload.py", 
  "output": [
    {
      "runtime": {
        "task_start": 1497185086, 
        "task_stop": 1497185101
      }, 
      "worker_id": "worker.1497031607.01035bc9.host.231181a3.10.10.1.7", 
      "task_state": "completed"
    }
  ], 
  "input": {
    "file_name": "bundle.EGAR00001117125.xml", 
    "object_id": "5142c507-f731-5454-8536-20d9fd01f58b", 
    "file_md5sum": "5d5393737efa606d8d7c33257f47e7a3", 
    "file": "/home/ubuntu/jtracker/worker.1497031607.01035bc9.host.231181a3.10.10.1.7/job.EGAR00001117125.LINC-JP.HCC102T.EGAN00001086046/task.prepare_metadata_xml/bundle.EGAR00001117125.xml", 
    "file_size": 3667, 
    "bundle_id": "EGAR00001117125"
  }, 
  "runtime": {
    "docker": null
  }
}