{
  "task": "xml_file_upload", 
  "depends_on": [
    "completed@prepare_metadata_xml"
  ], 
  "tool": "upload", 
  "command": "upload.py", 
  "output": [
    {
      "runtime": {
        "task_start": 1496943986, 
        "task_stop": 1496944000
      }, 
      "worker_id": "worker.1496933090.2b1766f3.host.63f39ac2.10.10.1.13", 
      "task_state": "completed"
    }
  ], 
  "input": {
    "file_name": "bundle.EGAR00001111302.xml", 
    "object_id": "2638f3a5-6d33-5410-b4ce-5c365233a23d", 
    "file_md5sum": "c9de8a3e74f668dbf91a5764f7d2ef2d", 
    "file": "/home/ubuntu/jtracker/worker.1496933090.2b1766f3.host.63f39ac2.10.10.1.13/job.EGAR00001111302.LINC-JP.HCC23T.EGAN00001085980/task.prepare_metadata_xml/bundle.EGAR00001111302.xml", 
    "file_size": 3665, 
    "bundle_id": "EGAR00001111302"
  }, 
  "runtime": {
    "docker": null
  }
}