{
  "task": "xml_file_upload", 
  "depends_on": [
    "completed@prepare_metadata_xml"
  ], 
  "tool": "upload", 
  "command": "upload.py", 
  "output": [
    {
      "runtime": {
        "task_start": 1497436931, 
        "task_stop": 1497436973
      }, 
      "worker_id": "worker.1497372592.ecbc8b0b.host.231181a3.10.10.1.7", 
      "task_state": "completed"
    }
  ], 
  "input": {
    "file_name": "bundle.EGAR00001195724.xml", 
    "object_id": "c9d27037-52d2-5f4e-a958-66fc85f2f841", 
    "file_md5sum": "80075d50a43130c1a9b5676ad70bfc3b", 
    "file": "/home/ubuntu/jtracker/worker.1497367460.7fd229eb.host.231181a3.10.10.1.7/job.EGAR00001195724.LINC-JP.HCC117T.EGAN00001196886/task.prepare_metadata_xml/bundle.EGAR00001195724.xml", 
    "file_size": 3511, 
    "bundle_id": "EGAR00001195724"
  }, 
  "runtime": {
    "docker": null
  }
}