{
  "task": "xml_file_upload", 
  "depends_on": [
    "completed@prepare_metadata_xml"
  ], 
  "tool": "upload", 
  "command": "upload.py", 
  "output": [
    {
      "runtime": {
        "task_start": 1495856572, 
        "task_stop": 1495856586
      }, 
      "worker_id": "worker.1495815557.f455bc66.host.bff27a91.10.10.0.223", 
      "task_state": "completed"
    }
  ], 
  "input": {
    "file_name": "bundle.EGAR00001254525.xml", 
    "object_id": "ad10d70c-1ded-5bb6-88d9-e09c7d95cbae", 
    "file_md5sum": "374b19a4f89d328ab690ee55b9561be2", 
    "file": "/home/ubuntu/jtracker/worker.1495815557.f455bc66.host.bff27a91.10.10.0.223/job.EGAR00001254525.PRAD-CA.CPCG0355-F1.EGAN00001220743/task.prepare_metadata_xml/bundle.EGAR00001254525.xml", 
    "file_size": 7505, 
    "bundle_id": "EGAR00001254525"
  }, 
  "runtime": {
    "docker": null
  }
}