{
  "task": "xml_file_upload", 
  "depends_on": [
    "completed@prepare_metadata_xml"
  ], 
  "tool": "upload", 
  "command": "upload.py", 
  "output": [
    {
      "runtime": {
        "task_start": 1496941497, 
        "task_stop": 1496941510
      }, 
      "worker_id": "worker.1496929466.e4bdd068.host.cfe46953.10.10.1.16", 
      "task_state": "completed"
    }
  ], 
  "input": {
    "file_name": "bundle.EGAR00001111443.xml", 
    "object_id": "c243048f-c495-50f9-9d6f-a13e92c6c3a8", 
    "file_md5sum": "9be537dba5122ccace470e850f873605", 
    "file": "/home/ubuntu/jtracker/worker.1496929466.e4bdd068.host.cfe46953.10.10.1.16/job.EGAR00001111443.LINC-JP.HCC24T.EGAN00001085981/task.prepare_metadata_xml/bundle.EGAR00001111443.xml", 
    "file_size": 3667, 
    "bundle_id": "EGAR00001111443"
  }, 
  "runtime": {
    "docker": null
  }
}