{
  "task": "xml_file_upload", 
  "depends_on": [
    "completed@prepare_metadata_xml"
  ], 
  "tool": "upload", 
  "command": "upload.py", 
  "output": [
    {
      "runtime": {
        "task_start": 1497048859, 
        "task_stop": 1497048879
      }, 
      "worker_id": "worker.1497031607.01035bc9.host.231181a3.10.10.1.7", 
      "task_state": "completed"
    }
  ], 
  "input": {
    "file_name": "bundle.EGAR00001200693.xml", 
    "object_id": "f5d393e8-4b63-50dd-9273-5bb6b5e83db4", 
    "file_md5sum": "50fcd8d0c4af06a776d9469afe2d25b1", 
    "file": "/home/ubuntu/jtracker/worker.1497031607.01035bc9.host.231181a3.10.10.1.7/job.EGAR00001200693.LINC-JP.HCC99T.EGAN00001196883/task.prepare_metadata_xml/bundle.EGAR00001200693.xml", 
    "file_size": 3505, 
    "bundle_id": "EGAR00001200693"
  }, 
  "runtime": {
    "docker": null
  }
}