{
  "task": "xml_file_upload", 
  "depends_on": [
    "completed@prepare_metadata_xml"
  ], 
  "tool": "upload", 
  "command": "upload.py", 
  "output": [
    {
      "runtime": {
        "task_start": 1496011600, 
        "task_stop": 1496011615
      }, 
      "worker_id": "worker.1495726527.79eafe9e.host.1faca8b3.10.10.0.231", 
      "task_state": "completed"
    }
  ], 
  "input": {
    "file_name": "bundle.EGAR00001222123.xml", 
    "object_id": "0bebf3b6-7694-5c93-9a19-11190332ed3f", 
    "file_md5sum": "ca9e2b6e63f9a8d06c4f60c2d60a8f8e", 
    "file": "/home/ubuntu/jtracker/worker.1495726527.79eafe9e.host.1faca8b3.10.10.0.231/job.EGAR00001222123.PRAD-CA.CPCG0365-B1.EGAN00001220760/task.prepare_metadata_xml/bundle.EGAR00001222123.xml", 
    "file_size": 7275, 
    "bundle_id": "EGAR00001222123"
  }, 
  "runtime": {
    "docker": null
  }
}