{
  "task": "xml_file_upload", 
  "depends_on": [
    "completed@prepare_metadata_xml"
  ], 
  "tool": "upload", 
  "command": "upload.py", 
  "output": [
    {
      "runtime": {
        "task_start": 1496071307, 
        "task_stop": 1496071324
      }, 
      "worker_id": "worker.1495657686.ff62a3f8.host.17c0e1e2.10.10.0.233", 
      "task_state": "completed"
    }
  ], 
  "input": {
    "file_name": "bundle.EGAR00001254568.xml", 
    "object_id": "6e972e01-42d7-5a4a-abc4-a01dde824a21", 
    "file_md5sum": "bca0e4b813df1e7ff8674f4d3b55174e", 
    "file": "/home/ubuntu/jtracker/worker.1495657686.ff62a3f8.host.17c0e1e2.10.10.0.233/job.EGAR00001254568.PRAD-CA.CPCG0368-F1.EGAN00001220765/task.prepare_metadata_xml/bundle.EGAR00001254568.xml", 
    "file_size": 7506, 
    "bundle_id": "EGAR00001254568"
  }, 
  "runtime": {
    "docker": null
  }
}