{
  "task": "prepare_metadata_xml", 
  "depends_on": null, 
  "tool": "prepare_metadata_xml", 
  "command": "prepare_metadata_xml.py", 
  "output": [
    {
      "xml_file_md5sum": "c13fdd1f5ae5c0d470ee8d328521de26", 
      "xml_file_name": "bundle.EGAR00001254493.xml", 
      "xml_file": "/home/ubuntu/jtracker/worker.1495821233.bc4e4ccd.host.2db3dbe6.10.10.0.227/job.EGAR00001254493.PRAD-CA.CPCG0350-F1.EGAN00001220735/task.prepare_metadata_xml/bundle.EGAR00001254493.xml", 
      "xml_file_size": 7507, 
      "worker_id": "worker.1495821233.bc4e4ccd.host.2db3dbe6.10.10.0.227", 
      "task_state": "completed", 
      "runtime": {
        "task_start": 1495866960, 
        "task_stop": 1495866961
      }
    }
  ], 
  "input": {
    "ega_metadata_repo": "https://raw.githubusercontent.com/icgc-dcc/ega-file-transfer/master/ega_xml/v20170522", 
    "ega_metadata_file_name": "bundle.EGAR00001254493.xml", 
    "ega_study_id": "EGAS00001000900", 
    "ega_dataset_id": "EGAD00001001094", 
    "ega_sample_id": "EGAN00001220735", 
    "ega_expriment_id": null, 
    "ega_analysis_id": null, 
    "bundle_id": "EGAR00001254493", 
    "project_code": "PRAD-CA", 
    "ega_run_id": "EGAR00001254493"
  }, 
  "runtime": {
    "docker": null
  }
}