{
  "task": "xml_file_upload", 
  "depends_on": [
    "completed@prepare_metadata_xml"
  ], 
  "tool": "upload", 
  "command": "upload.py", 
  "output": [
    {
      "runtime": {
        "task_start": 1495856788, 
        "task_stop": 1495856802
      }, 
      "worker_id": "worker.1495806788.855dddef.host.ff63aa11.10.10.0.225", 
      "task_state": "completed"
    }
  ], 
  "input": {
    "file_name": "bundle.EGAR00001222195.xml", 
    "object_id": "17907574-ea8e-5a6a-b3e4-76ab78b4cd8b", 
    "file_md5sum": "fc5eec30e7f174b6a2af233965597246", 
    "file": "/home/ubuntu/jtracker/worker.1495806788.855dddef.host.ff63aa11.10.10.0.225/job.EGAR00001222195.PRAD-CA.CPCG0414-B1.EGAN00001220810/task.prepare_metadata_xml/bundle.EGAR00001222195.xml", 
    "file_size": 7278, 
    "bundle_id": "EGAR00001222195"
  }, 
  "runtime": {
    "docker": null
  }
}