{
  "task": "xml_file_upload", 
  "depends_on": [
    "completed@prepare_metadata_xml"
  ], 
  "tool": "upload", 
  "command": "upload.py", 
  "output": [
    {
      "runtime": {
        "task_start": 1496960241, 
        "task_stop": 1496960254
      }, 
      "worker_id": "worker.1496935968.c64dab79.host.231181a3.10.10.1.7", 
      "task_state": "completed"
    }
  ], 
  "input": {
    "file_name": "bundle.EGAR00001111268.xml", 
    "object_id": "b24c8583-8961-56a9-ab7b-eb6d334d38cc", 
    "file_md5sum": "ed1beeb8de6d34cfbf172957a571afa5", 
    "file": "/home/ubuntu/jtracker/worker.1496935968.c64dab79.host.231181a3.10.10.1.7/job.EGAR00001111268.LINC-JP.HCC23T.EGAN00001085980/task.prepare_metadata_xml/bundle.EGAR00001111268.xml", 
    "file_size": 3665, 
    "bundle_id": "EGAR00001111268"
  }, 
  "runtime": {
    "docker": null
  }
}