{
  "task": "xml_file_upload", 
  "depends_on": [
    "completed@prepare_metadata_xml"
  ], 
  "tool": "upload", 
  "command": "upload.py", 
  "output": [
    {
      "runtime": {
        "task_start": 1496027468, 
        "task_stop": 1496027485
      }, 
      "worker_id": "worker.1495972695.f6a719ce.host.bf6252ab.10.0.0.145", 
      "task_state": "completed"
    }
  ], 
  "input": {
    "file_name": "bundle.EGAR00001250502.xml", 
    "object_id": "da194f0b-1339-5720-b298-8adb0ba10820", 
    "file_md5sum": "29deb2fbee32722d2bcd1e9a6acd0141", 
    "file": "/data/jt_home/worker.1495972695.f6a719ce.host.bf6252ab.10.0.0.145/job.EGAR00001250502.PRAD-CA.CPCG0006-F1.EGAN00001220576/task.prepare_metadata_xml/bundle.EGAR00001250502.xml", 
    "file_size": 7378, 
    "bundle_id": "EGAR00001250502"
  }, 
  "runtime": {
    "docker": null
  }
}