{
  "task": "xml_file_upload", 
  "depends_on": [
    "completed@prepare_metadata_xml"
  ], 
  "tool": "upload", 
  "command": "upload.py", 
  "output": [
    {
      "runtime": {
        "task_start": 1495896631, 
        "task_stop": 1495896646
      }, 
      "worker_id": "worker.1495821233.bc4e4ccd.host.2db3dbe6.10.10.0.227", 
      "task_state": "completed"
    }
  ], 
  "input": {
    "file_name": "bundle.EGAR00001222049.xml", 
    "object_id": "858191c4-d457-52e6-89c2-4e8e681a951f", 
    "file_md5sum": "0c53989e3c68d03738eecd86f58890f2", 
    "file": "/home/ubuntu/jtracker/worker.1495821233.bc4e4ccd.host.2db3dbe6.10.10.0.227/job.EGAR00001222049.PRAD-CA.CPCG0324-B1.EGAN00001220710/task.prepare_metadata_xml/bundle.EGAR00001222049.xml", 
    "file_size": 7267, 
    "bundle_id": "EGAR00001222049"
  }, 
  "runtime": {
    "docker": null
  }
}